oandacli/__init__.py
oandacli/call/__init__.py
oandacli/call/candle.py
oandacli/call/info.py
oandacli/call/order.py
oandacli/call/plot.py
oandacli/call/streamer.py
oandacli/call/transaction.py
oandacli/cli/__init__.py
oandacli/cli/main.py
oandacli/static/create_tables.sql
oandacli/static/default_oanda.yml
oandacli/util/__init__.py
oandacli/util/config.py
oandacli/util/logger.py
oanda_cli-1.1.3.dist-info/LICENSE
oanda_cli-1.1.3.dist-info/METADATA
oanda_cli-1.1.3.dist-info/WHEEL
oanda_cli-1.1.3.dist-info/entry_points.txt
oanda_cli-1.1.3.dist-info/top_level.txt
oanda_cli-1.1.3.dist-info/RECORD
