Metadata-Version: 2.1
Name: oanda-cli
Version: 1.1.3
Summary: Command Line Interface for Oanda API
Home-page: https://github.com/dceoy/oanda-cli
Author: Daichi Narushima
Author-email: dnarsil+github@gmail.com
License: UNKNOWN
Platform: UNKNOWN
Classifier: Development Status :: 4 - Beta
Classifier: Environment :: Console
Classifier: Intended Audience :: Developers
Classifier: Intended Audience :: Financial and Insurance Industry
Classifier: License :: OSI Approved :: GNU General Public License v3 (GPLv3)
Classifier: Operating System :: POSIX :: Linux
Classifier: Operating System :: MacOS
Classifier: Programming Language :: Python :: 3
Classifier: Topic :: Office/Business :: Financial :: Investment
Requires-Python: >=3.6
License-File: LICENSE
Requires-Dist: docopt
Requires-Dist: pandas
Requires-Dist: pyyaml
Requires-Dist: redis
Requires-Dist: seaborn
Requires-Dist: v20
